[
    {
        "school": "QNS01",
        "major": "KORE",
        "room_num": "28426",
        "room_desc": "Advanced Korean I"
    },
    {
        "school": "QNS01",
        "major": "KORE",
        "room_num": "28427",
        "room_desc": "Advanced Korean II"
    },
    {
        "school": "QNS01",
        "major": "KORE",
        "room_num": "28428",
        "room_desc": "Advanced Korean Through Film"
    },
    {
        "school": "QNS01",
        "major": "KORE",
        "room_num": "28429",
        "room_desc": "Elementary Korean I"
    },
    {
        "school": "QNS01",
        "major": "KORE",
        "room_num": "28430",
        "room_desc": "Elementary Korean II"
    },
    {
        "school": "QNS01",
        "major": "KORE",
        "room_num": "28431",
        "room_desc": "Intermediate Korean I"
    },
    {
        "school": "QNS01",
        "major": "KORE",
        "room_num": "28432",
        "room_desc": "Intermediate Korean II"
    },
    {
        "school": "QNS01",
        "major": "KORE",
        "room_num": "28433",
        "room_desc": "Intro Appli Korean Linguistics"
    },
    {
        "school": "QNS01",
        "major": "KORE",
        "room_num": "28434",
        "room_desc": "Intro Formal Korean Linguistic"
    },
    {
        "school": "QNS01",
        "major": "KORE",
        "room_num": "28435",
        "room_desc": "Read & Writing Chinese Char I"
    },
    {
        "school": "QNS01",
        "major": "KORE",
        "room_num": "28436",
        "room_desc": "Read & Writing Chinese Char ll"
    },
    {
        "school": "QNS01",
        "major": "KORE",
        "room_num": "28437",
        "room_desc": "Readings in Korean"
    }
]