[
    {
        "school": "MEC01",
        "major": "COMM",
        "room_num": "78292",
        "room_desc": "Comm Skills I"
    },
    {
        "school": "MEC01",
        "major": "COMM",
        "room_num": "78293",
        "room_desc": "Comm Skills II"
    },
    {
        "school": "MEC01",
        "major": "COMM",
        "room_num": "78294",
        "room_desc": "Comm Skills Lab I"
    },
    {
        "school": "MEC01",
        "major": "COMM",
        "room_num": "78295",
        "room_desc": "Comm Skills Lab II"
    },
    {
        "school": "MEC01",
        "major": "COMM",
        "room_num": "78296",
        "room_desc": "Communications I"
    },
    {
        "school": "MEC01",
        "major": "COMM",
        "room_num": "78297",
        "room_desc": "Communications II"
    }
]