[
    {
        "school": "BMC01",
        "major": "AFST",
        "room_num": "17156",
        "room_desc": "20th Cent Afr Devel"
    },
    {
        "school": "BMC01",
        "major": "AFST",
        "room_num": "17157",
        "room_desc": "Af-Amer His To 1865"
    },
    {
        "school": "BMC01",
        "major": "AFST",
        "room_num": "17158",
        "room_desc": "Afl Directed Study"
    },
    {
        "school": "BMC01",
        "major": "AFST",
        "room_num": "17159",
        "room_desc": "Africa 1500 To Pres"
    },
    {
        "school": "BMC01",
        "major": "AFST",
        "room_num": "17160",
        "room_desc": "African Art (Same as ART 801)"
    },
    {
        "school": "BMC01",
        "major": "AFST",
        "room_num": "17161",
        "room_desc": "African-American Art"
    },
    {
        "school": "BMC01",
        "major": "AFST",
        "room_num": "17162",
        "room_desc": "African-American Hist (Honors)"
    },
    {
        "school": "BMC01",
        "major": "AFST",
        "room_num": "17163",
        "room_desc": "African-American History"
    },
    {
        "school": "BMC01",
        "major": "AFST",
        "room_num": "17164",
        "room_desc": "Afro-Latino Directed Study"
    },
    {
        "school": "BMC01",
        "major": "AFST",
        "room_num": "17165",
        "room_desc": "Black Directed Study"
    },
    {
        "school": "BMC01",
        "major": "AFST",
        "room_num": "17166",
        "room_desc": "Blk Directed Study"
    },
    {
        "school": "BMC01",
        "major": "AFST",
        "room_num": "17167",
        "room_desc": "Blk Man In Society"
    },
    {
        "school": "BMC01",
        "major": "AFST",
        "room_num": "17168",
        "room_desc": "Blk Man In Society (Honors)"
    },
    {
        "school": "BMC01",
        "major": "AFST",
        "room_num": "17169",
        "room_desc": "Blk Women Amer/Cari"
    },
    {
        "school": "BMC01",
        "major": "AFST",
        "room_num": "17170",
        "room_desc": "Blk Women Amer/Cari (Honors)"
    },
    {
        "school": "BMC01",
        "major": "AFST",
        "room_num": "17171",
        "room_desc": "Caribbean Black Lit"
    },
    {
        "school": "BMC01",
        "major": "AFST",
        "room_num": "17172",
        "room_desc": "Caribbean History"
    },
    {
        "school": "BMC01",
        "major": "AFST",
        "room_num": "17173",
        "room_desc": "Community Problems"
    },
    {
        "school": "BMC01",
        "major": "AFST",
        "room_num": "17174",
        "room_desc": "Comp.Ethnic Studies"
    },
    {
        "school": "BMC01",
        "major": "AFST",
        "room_num": "17175",
        "room_desc": "Contemporary Black Writers"
    },
    {
        "school": "BMC01",
        "major": "AFST",
        "room_num": "17176",
        "room_desc": "Contmp Blk Writers"
    },
    {
        "school": "BMC01",
        "major": "AFST",
        "room_num": "17177",
        "room_desc": "Dom Rep Econ Devel"
    },
    {
        "school": "BMC01",
        "major": "AFST",
        "room_num": "17178",
        "room_desc": "Economics of Urban Communities"
    },
    {
        "school": "BMC01",
        "major": "AFST",
        "room_num": "17179",
        "room_desc": "Haitian History and Culture"
    },
    {
        "school": "BMC01",
        "major": "AFST",
        "room_num": "17180",
        "room_desc": "Hist Of African Civilizations"
    },
    {
        "school": "BMC01",
        "major": "AFST",
        "room_num": "17181",
        "room_desc": "History of Black Theater"
    },
    {
        "school": "BMC01",
        "major": "AFST",
        "room_num": "17182",
        "room_desc": "Hlth Prob Urban Com"
    },
    {
        "school": "BMC01",
        "major": "AFST",
        "room_num": "17183",
        "room_desc": "Introduction to Ethnic Studies"
    },
    {
        "school": "BMC01",
        "major": "AFST",
        "room_num": "17184",
        "room_desc": "Mod Blk Pol Thought"
    },
    {
        "school": "BMC01",
        "major": "AFST",
        "room_num": "17185",
        "room_desc": "Political Eco Carib"
    },
    {
        "school": "BMC01",
        "major": "AFST",
        "room_num": "17186",
        "room_desc": "Puerto Rican Culture Folklore"
    },
    {
        "school": "BMC01",
        "major": "AFST",
        "room_num": "17187",
        "room_desc": "Research and Writing Methods"
    },
    {
        "school": "BMC01",
        "major": "AFST",
        "room_num": "17188",
        "room_desc": "Social Blk Urb Com"
    },
    {
        "school": "BMC01",
        "major": "AFST",
        "room_num": "17189",
        "room_desc": "The Black Experience in Africa"
    },
    {
        "school": "BMC01",
        "major": "AFST",
        "room_num": "17190",
        "room_desc": "The Contemporary Black Family"
    },
    {
        "school": "BMC01",
        "major": "AFST",
        "room_num": "17191",
        "room_desc": "The Roles Of Women"
    }
]