[
    {
        "school": "BMC01",
        "major": "SOCI",
        "room_num": "19091",
        "room_desc": "Art19092: SOCI,\"Blk Man In Society"
    },
    {
        "school": "BMC01",
        "major": "SOCI",
        "room_num": "19093",
        "room_desc": "Comparative Ethnic Studies"
    },
    {
        "school": "BMC01",
        "major": "SOCI",
        "room_num": "19094",
        "room_desc": "Gender and Society"
    },
    {
        "school": "BMC01",
        "major": "SOCI",
        "room_num": "19095",
        "room_desc": "Hlth Prob Urban Com"
    },
    {
        "school": "BMC01",
        "major": "SOCI",
        "room_num": "19096",
        "room_desc": "Introduction to Sociology"
    },
    {
        "school": "BMC01",
        "major": "SOCI",
        "room_num": "19097",
        "room_desc": "P.R Exp In Urban Us"
    },
    {
        "school": "BMC01",
        "major": "SOCI",
        "room_num": "19098",
        "room_desc": "Race and Ethnicity"
    },
    {
        "school": "BMC01",
        "major": "SOCI",
        "room_num": "19099",
        "room_desc": "Race and Ethnicity (Honors)"
    },
    {
        "school": "BMC01",
        "major": "SOCI",
        "room_num": "19100",
        "room_desc": "SOC Directed Study"
    },
    {
        "school": "BMC01",
        "major": "SOCI",
        "room_num": "19101",
        "room_desc": "Soc Directed Study"
    },
    {
        "school": "BMC01",
        "major": "SOCI",
        "room_num": "19102",
        "room_desc": "Social Problems"
    },
    {
        "school": "BMC01",
        "major": "SOCI",
        "room_num": "19103",
        "room_desc": "Sociology Black Urb"
    },
    {
        "school": "BMC01",
        "major": "SOCI",
        "room_num": "19104",
        "room_desc": "Sociology Capstone"
    },
    {
        "school": "BMC01",
        "major": "SOCI",
        "room_num": "19105",
        "room_desc": "Sociology Directed Study"
    },
    {
        "school": "BMC01",
        "major": "SOCI",
        "room_num": "19106",
        "room_desc": "Sociology Workshop"
    },
    {
        "school": "BMC01",
        "major": "SOCI",
        "room_num": "19107",
        "room_desc": "Sociology of Health & Illness"
    },
    {
        "school": "BMC01",
        "major": "SOCI",
        "room_num": "19108",
        "room_desc": "Sociology of Urban Education"
    },
    {
        "school": "BMC01",
        "major": "SOCI",
        "room_num": "19109",
        "room_desc": "Technological Society (Honors)"
    },
    {
        "school": "BMC01",
        "major": "SOCI",
        "room_num": "19110",
        "room_desc": "The Contemporary Black Family"
    },
    {
        "school": "BMC01",
        "major": "SOCI",
        "room_num": "19111",
        "room_desc": "The Family"
    },
    {
        "school": "BMC01",
        "major": "SOCI",
        "room_num": "19112",
        "room_desc": "The Latino Experience In U.S."
    },
    {
        "school": "BMC01",
        "major": "SOCI",
        "room_num": "19113",
        "room_desc": "The Puerto Rican Family"
    },
    {
        "school": "BMC01",
        "major": "SOCI",
        "room_num": "19114",
        "room_desc": "Understanding Techno Society"
    },
    {
        "school": "BMC01",
        "major": "SOCI",
        "room_num": "19115",
        "room_desc": "Urban Sociology"
    },
    {
        "school": "BMC01",
        "major": "SOCI",
        "room_num": "19116",
        "room_desc": "Urban Sociology (Honors)"
    }
]