[
    {
        "major": "MAHC",
        "room_num": "53836",
        "desc": "Arts in NYC"
    },
    {
        "major": "MAHC",
        "room_num": "53837",
        "desc": "Peopling: NY"
    },
    {
        "major": "MAHC",
        "room_num": "53838",
        "desc": "Science and Technology - NYC"
    },
    {
        "major": "MAHC",
        "room_num": "53839",
        "desc": "Shpg the Fut:Ct"
    },
    {
        "major": "MAHC",
        "room_num": "53840",
        "desc": "The Law of Contracts and Torts"
    }
]