[
    {
        "major": "HIST",
        "room_num": "67139",
        "desc": "20 Cent Europe Soc"
    },
    {
        "major": "HIST",
        "room_num": "67140",
        "desc": "20 Century China"
    },
    {
        "major": "HIST",
        "room_num": "67141",
        "desc": "20th Century Europe"
    },
    {
        "major": "HIST",
        "room_num": "67142",
        "desc": "42  Ooo"
    },
    {
        "major": "HIST",
        "room_num": "67143",
        "desc": "Africa Encounters Europe"
    },
    {
        "major": "HIST",
        "room_num": "67144",
        "desc": "Afro-Amer Hist I"
    },
    {
        "major": "HIST",
        "room_num": "67145",
        "desc": "Afro-Amer Hist II"
    },
    {
        "major": "HIST",
        "room_num": "67146",
        "desc": "Afro-Amer Origins"
    },
    {
        "major": "HIST",
        "room_num": "67147",
        "desc": "Afro-Amer Survey"
    },
    {
        "major": "HIST",
        "room_num": "67148",
        "desc": "Age of Revolutions: 1765-1820"
    },
    {
        "major": "HIST",
        "room_num": "67149",
        "desc": "Age of the French Revolution"
    },
    {
        "major": "HIST",
        "room_num": "67150",
        "desc": "Amer Rep 1788-1850"
    },
    {
        "major": "HIST",
        "room_num": "67151",
        "desc": "American Civiliztn"
    },
    {
        "major": "HIST",
        "room_num": "67152",
        "desc": "American Economic History"
    },
    {
        "major": "HIST",
        "room_num": "67153",
        "desc": "American Ideas"
    },
    {
        "major": "HIST",
        "room_num": "67154",
        "desc": "American Landscapes"
    },
    {
        "major": "HIST",
        "room_num": "67155",
        "desc": "Americn Revolution"
    },
    {
        "major": "HIST",
        "room_num": "67156",
        "desc": "Ancient Jewish Hst"
    },
    {
        "major": "HIST",
        "room_num": "67157",
        "desc": "Ancient Near East"
    },
    {
        "major": "HIST",
        "room_num": "67158",
        "desc": "Archive Internship"
    },
    {
        "major": "HIST",
        "room_num": "67159",
        "desc": "Asian American History"
    },
    {
        "major": "HIST",
        "room_num": "67160",
        "desc": "Asian Civilization"
    },
    {
        "major": "HIST",
        "room_num": "67161",
        "desc": "Asian Tigers since 1945"
    },
    {
        "major": "HIST",
        "room_num": "67162",
        "desc": "Black Thought African Diaspora"
    },
    {
        "major": "HIST",
        "room_num": "67163",
        "desc": "Blk Thgt Afrn Diaspo"
    },
    {
        "major": "HIST",
        "room_num": "67164",
        "desc": "Brit Hst/1700-1900"
    },
    {
        "major": "HIST",
        "room_num": "67165",
        "desc": "Brit Hst/Post 1900"
    },
    {
        "major": "HIST",
        "room_num": "67166",
        "desc": "Byzantine Thougt&Civ"
    },
    {
        "major": "HIST",
        "room_num": "67167",
        "desc": "Chinese Civilization"
    },
    {
        "major": "HIST",
        "room_num": "67168",
        "desc": "Classcl&Hellistc His"
    },
    {
        "major": "HIST",
        "room_num": "67169",
        "desc": "Colonialism & African Exper"
    },
    {
        "major": "HIST",
        "room_num": "67170",
        "desc": "Comparative Ancient Religion"
    },
    {
        "major": "HIST",
        "room_num": "67171",
        "desc": "Comparative Urban History"
    },
    {
        "major": "HIST",
        "room_num": "67172",
        "desc": "Contemporary African Issues"
    },
    {
        "major": "HIST",
        "room_num": "67173",
        "desc": "Early Mod Eur Hist"
    },
    {
        "major": "HIST",
        "room_num": "67174",
        "desc": "Early Modern England"
    },
    {
        "major": "HIST",
        "room_num": "67175",
        "desc": "Early Modern Europe"
    },
    {
        "major": "HIST",
        "room_num": "67176",
        "desc": "Economic Hist of Soviet Russia"
    },
    {
        "major": "HIST",
        "room_num": "67177",
        "desc": "Environmental History"
    },
    {
        "major": "HIST",
        "room_num": "67178",
        "desc": "Eur Disc Amerca 1492"
    },
    {
        "major": "HIST",
        "room_num": "67179",
        "desc": "Eur Hist From Ren"
    },
    {
        "major": "HIST",
        "room_num": "67180",
        "desc": "Europe Since 1815"
    },
    {
        "major": "HIST",
        "room_num": "67181",
        "desc": "Foundations of Modern Society"
    },
    {
        "major": "HIST",
        "room_num": "67182",
        "desc": "Freshman Seminar in History"
    },
    {
        "major": "HIST",
        "room_num": "67183",
        "desc": "Garvey And Dubois"
    },
    {
        "major": "HIST",
        "room_num": "67184",
        "desc": "Gender/Consciousness"
    },
    {
        "major": "HIST",
        "room_num": "67185",
        "desc": "Greece"
    },
    {
        "major": "HIST",
        "room_num": "67186",
        "desc": "Greek and Roman Mythology"
    },
    {
        "major": "HIST",
        "room_num": "67187",
        "desc": "HST Independent Study"
    },
    {
        "major": "HIST",
        "room_num": "67188",
        "desc": "Hist Of Nineteenth-Cent Europe"
    },
    {
        "major": "HIST",
        "room_num": "67189",
        "desc": "Hist Of The South"
    },
    {
        "major": "HIST",
        "room_num": "67190",
        "desc": "Hist Of Us Education"
    },
    {
        "major": "HIST",
        "room_num": "67191",
        "desc": "Hist Themes & Interp"
    },
    {
        "major": "HIST",
        "room_num": "67192",
        "desc": "Hist of The Balkans: 1453-Pres"
    },
    {
        "major": "HIST",
        "room_num": "67193",
        "desc": "Historical Method"
    },
    {
        "major": "HIST",
        "room_num": "67194",
        "desc": "Historicl Research"
    },
    {
        "major": "HIST",
        "room_num": "67195",
        "desc": "Histories of Sexuality iModWrl"
    },
    {
        "major": "HIST",
        "room_num": "67196",
        "desc": "Historiography"
    },
    {
        "major": "HIST",
        "room_num": "67197",
        "desc": "History Credit"
    },
    {
        "major": "HIST",
        "room_num": "67198",
        "desc": "History Elective Credit"
    },
    {
        "major": "HIST",
        "room_num": "67199",
        "desc": "History Grad Credit"
    },
    {
        "major": "HIST",
        "room_num": "67200",
        "desc": "History Graduate Credit"
    },
    {
        "major": "HIST",
        "room_num": "67201",
        "desc": "History Ind Study"
    },
    {
        "major": "HIST",
        "room_num": "67202",
        "desc": "History Independent Study"
    },
    {
        "major": "HIST",
        "room_num": "67203",
        "desc": "History Internship"
    },
    {
        "major": "HIST",
        "room_num": "67204",
        "desc": "History of Africa"
    },
    {
        "major": "HIST",
        "room_num": "67205",
        "desc": "History of American Women"
    },
    {
        "major": "HIST",
        "room_num": "67206",
        "desc": "History of Christianity"
    },
    {
        "major": "HIST",
        "room_num": "67207",
        "desc": "History of Italy"
    },
    {
        "major": "HIST",
        "room_num": "67208",
        "desc": "History of Modern India"
    },
    {
        "major": "HIST",
        "room_num": "67209",
        "desc": "History of Modern Russia"
    },
    {
        "major": "HIST",
        "room_num": "67210",
        "desc": "History of N.Y.C."
    },
    {
        "major": "HIST",
        "room_num": "67211",
        "desc": "History of New York"
    },
    {
        "major": "HIST",
        "room_num": "67212",
        "desc": "History of Science"
    },
    {
        "major": "HIST",
        "room_num": "67213",
        "desc": "History of Staten Island"
    },
    {
        "major": "HIST",
        "room_num": "67214",
        "desc": "History of Work"
    },
    {
        "major": "HIST",
        "room_num": "67215",
        "desc": "History of the Caribbean"
    },
    {
        "major": "HIST",
        "room_num": "67216",
        "desc": "History of the U.S. City"
    },
    {
        "major": "HIST",
        "room_num": "67217",
        "desc": "Holocaust in European History"
    },
    {
        "major": "HIST",
        "room_num": "67218",
        "desc": "Hst Relgn Antquity"
    },
    {
        "major": "HIST",
        "room_num": "67219",
        "desc": "Imperial Russia"
    },
    {
        "major": "HIST",
        "room_num": "67220",
        "desc": "Imperialism"
    },
    {
        "major": "HIST",
        "room_num": "67221",
        "desc": "Individ/Society Ancient Greece"
    },
    {
        "major": "HIST",
        "room_num": "67222",
        "desc": "Intro Archiv Studies"
    },
    {
        "major": "HIST",
        "room_num": "67223",
        "desc": "Intro Archival Stdy"
    },
    {
        "major": "HIST",
        "room_num": "67224",
        "desc": "Intro Women\u2019S Hist"
    },
    {
        "major": "HIST",
        "room_num": "67225",
        "desc": "Introduction To Museum Studies"
    },
    {
        "major": "HIST",
        "room_num": "67226",
        "desc": "Islam: Religion and Culture"
    },
    {
        "major": "HIST",
        "room_num": "67227",
        "desc": "Italian American History"
    },
    {
        "major": "HIST",
        "room_num": "67228",
        "desc": "Japanese Civilization"
    },
    {
        "major": "HIST",
        "room_num": "67229",
        "desc": "Jewish History"
    },
    {
        "major": "HIST",
        "room_num": "67230",
        "desc": "Late Imperial China"
    },
    {
        "major": "HIST",
        "room_num": "67231",
        "desc": "Ma Portfolio Prep Seminar"
    },
    {
        "major": "HIST",
        "room_num": "67232",
        "desc": "Medieval Cities"
    },
    {
        "major": "HIST",
        "room_num": "67233",
        "desc": "Medieval England"
    },
    {
        "major": "HIST",
        "room_num": "67234",
        "desc": "Medieval Russia"
    },
    {
        "major": "HIST",
        "room_num": "67235",
        "desc": "Medieval Thought"
    },
    {
        "major": "HIST",
        "room_num": "67236",
        "desc": "Medievl Inherit I"
    },
    {
        "major": "HIST",
        "room_num": "67237",
        "desc": "Medievl Inherit II"
    },
    {
        "major": "HIST",
        "room_num": "67238",
        "desc": "Medv Blkns 1204-1481"
    },
    {
        "major": "HIST",
        "room_num": "67239",
        "desc": "Mod Latin America"
    },
    {
        "major": "HIST",
        "room_num": "67240",
        "desc": "Modern China"
    },
    {
        "major": "HIST",
        "room_num": "67241",
        "desc": "Modern English History"
    },
    {
        "major": "HIST",
        "room_num": "67242",
        "desc": "Modern Germany"
    },
    {
        "major": "HIST",
        "room_num": "67243",
        "desc": "Modern Japan"
    },
    {
        "major": "HIST",
        "room_num": "67244",
        "desc": "Modern World War"
    },
    {
        "major": "HIST",
        "room_num": "67245",
        "desc": "Movemnts/Indep Afrca"
    },
    {
        "major": "HIST",
        "room_num": "67246",
        "desc": "Museum Studies"
    },
    {
        "major": "HIST",
        "room_num": "67247",
        "desc": "Nazi Germany"
    },
    {
        "major": "HIST",
        "room_num": "67248",
        "desc": "New Approaches to History"
    },
    {
        "major": "HIST",
        "room_num": "67249",
        "desc": "Nineteenth-Century Europe"
    },
    {
        "major": "HIST",
        "room_num": "67250",
        "desc": "Ny City Hst & Prob"
    },
    {
        "major": "HIST",
        "room_num": "67251",
        "desc": "Oral Hst Mthds67252: HIST,\"Past and Present"
    },
    {
        "major": "HIST",
        "room_num": "67253",
        "desc": "Peoples and Cultures of Africa"
    },
    {
        "major": "HIST",
        "room_num": "67254",
        "desc": "Pirates in the Early Mod World"
    },
    {
        "major": "HIST",
        "room_num": "67255",
        "desc": "Preparation of Thesis Proposal"
    },
    {
        "major": "HIST",
        "room_num": "67256",
        "desc": "Problems Amer City"
    },
    {
        "major": "HIST",
        "room_num": "67257",
        "desc": "Progressive Era"
    },
    {
        "major": "HIST",
        "room_num": "67258",
        "desc": "Project Seminal"
    },
    {
        "major": "HIST",
        "room_num": "67259",
        "desc": "Psycho-History"
    },
    {
        "major": "HIST",
        "room_num": "67260",
        "desc": "Public Hst Practicum/Intern"
    },
    {
        "major": "HIST",
        "room_num": "67261",
        "desc": "Reacting to the Past"
    },
    {
        "major": "HIST",
        "room_num": "67262",
        "desc": "Religion in America"
    },
    {
        "major": "HIST",
        "room_num": "67263",
        "desc": "Renaisnce/Refrmatn"
    },
    {
        "major": "HIST",
        "room_num": "67264",
        "desc": "Resistance and Rev in Lat Amer"
    },
    {
        "major": "HIST",
        "room_num": "67265",
        "desc": "Revolutns Analysis"
    },
    {
        "major": "HIST",
        "room_num": "67266",
        "desc": "Roman Repub&Imp Hist"
    },
    {
        "major": "HIST",
        "room_num": "67267",
        "desc": "Russ Rev 1917-1991"
    },
    {
        "major": "HIST",
        "room_num": "67268",
        "desc": "Seminar in Public History"
    },
    {
        "major": "HIST",
        "room_num": "67269",
        "desc": "Semnar/Adv Hst Study"
    },
    {
        "major": "HIST",
        "room_num": "67270",
        "desc": "Soc&Pol Ideologies Mod World"
    },
    {
        "major": "HIST",
        "room_num": "67271",
        "desc": "Soc/Pol Mod Europe"
    },
    {
        "major": "HIST",
        "room_num": "67272",
        "desc": "Society and Culture in the US"
    },
    {
        "major": "HIST",
        "room_num": "67273",
        "desc": "Soviet Union&Russia"
    },
    {
        "major": "HIST",
        "room_num": "67274",
        "desc": "Spain and Its World67275: HIST,\"THE HIST OF 20th CENT EUROPE"
    },
    {
        "major": "HIST",
        "room_num": "67276",
        "desc": "The 1960s in Europe"
    },
    {
        "major": "HIST",
        "room_num": "67277",
        "desc": "The African Diaspora"
    },
    {
        "major": "HIST",
        "room_num": "67278",
        "desc": "The American Dream"
    },
    {
        "major": "HIST",
        "room_num": "67279",
        "desc": "The Atlantic World"
    },
    {
        "major": "HIST",
        "room_num": "67280",
        "desc": "The Classical Inheritance"
    },
    {
        "major": "HIST",
        "room_num": "67281",
        "desc": "The Cold War"
    },
    {
        "major": "HIST",
        "room_num": "67282",
        "desc": "The Hist of Amer Immigration"
    },
    {
        "major": "HIST",
        "room_num": "67283",
        "desc": "The Late Antique World"
    },
    {
        "major": "HIST",
        "room_num": "67284",
        "desc": "The Middle East and Europe"
    },
    {
        "major": "HIST",
        "room_num": "67285",
        "desc": "The Modern Middle East"
    },
    {
        "major": "HIST",
        "room_num": "67286",
        "desc": "The Recovery of Women\u2019s Past"
    },
    {
        "major": "HIST",
        "room_num": "67287",
        "desc": "The Roman World"
    },
    {
        "major": "HIST",
        "room_num": "67288",
        "desc": "The Silk Road"
    },
    {
        "major": "HIST",
        "room_num": "67289",
        "desc": "The Supreme Court"
    },
    {
        "major": "HIST",
        "room_num": "67290",
        "desc": "The World Since 1900"
    },
    {
        "major": "HIST",
        "room_num": "67291",
        "desc": "The World of Tokugawa Japan"
    },
    {
        "major": "HIST",
        "room_num": "67292",
        "desc": "The World of the 21st Century"
    },
    {
        "major": "HIST",
        "room_num": "67293",
        "desc": "Themes Am Women Hist"
    },
    {
        "major": "HIST",
        "room_num": "67294",
        "desc": "Themes in Byzantine History"
    },
    {
        "major": "HIST",
        "room_num": "67295",
        "desc": "Themes in U.S Hist: 1914-1945"
    },
    {
        "major": "HIST",
        "room_num": "67296",
        "desc": "Thesis Tutorial Seminar"
    },
    {
        "major": "HIST",
        "room_num": "67297",
        "desc": "Topics Ancient/Medieval Hist"
    },
    {
        "major": "HIST",
        "room_num": "67298",
        "desc": "Topics Latin American History"
    },
    {
        "major": "HIST",
        "room_num": "67299",
        "desc": "Topics Modern European History"
    },
    {
        "major": "HIST",
        "room_num": "67300",
        "desc": "Topics in Caribbean History"
    },
    {
        "major": "HIST",
        "room_num": "67301",
        "desc": "Topics in U.S. History to 1865"
    },
    {
        "major": "HIST",
        "room_num": "67302",
        "desc": "Topics in US Hist from 1865"
    },
    {
        "major": "HIST",
        "room_num": "67303",
        "desc": "Tp Anc Eur Medtrn Hs"
    },
    {
        "major": "HIST",
        "room_num": "67304",
        "desc": "Tp Erly Mod Eur Hst"
    },
    {
        "major": "HIST",
        "room_num": "67305",
        "desc": "Tp Med Eur&Medtrn Hs"
    },
    {
        "major": "HIST",
        "room_num": "67306",
        "desc": "Tpcs Eur Hist To Ren"
    },
    {
        "major": "HIST",
        "room_num": "67307",
        "desc": "Tpcs Hist East Asia"
    },
    {
        "major": "HIST",
        "room_num": "67308",
        "desc": "Tpcs Hist Mid East"
    },
    {
        "major": "HIST",
        "room_num": "67309",
        "desc": "Tpcs Hist Of Africa"
    },
    {
        "major": "HIST",
        "room_num": "67310",
        "desc": "Tpcs Hist South Asia"
    },
    {
        "major": "HIST",
        "room_num": "67311",
        "desc": "Tudor and Stuart History"
    },
    {
        "major": "HIST",
        "room_num": "67312",
        "desc": "U S  Hist Since 1945"
    },
    {
        "major": "HIST",
        "room_num": "67313",
        "desc": "U S Foreign Policy"
    },
    {
        "major": "HIST",
        "room_num": "67314",
        "desc": "U S His: 1607-1865"
    },
    {
        "major": "HIST",
        "room_num": "67315",
        "desc": "U.S. History Since 1865"
    },
    {
        "major": "HIST",
        "room_num": "67316",
        "desc": "U.S. History to 1865"
    },
    {
        "major": "HIST",
        "room_num": "67317",
        "desc": "U.S. History: 1900-1940"
    },
    {
        "major": "HIST",
        "room_num": "67318",
        "desc": "US History:1865-Present"
    },
    {
        "major": "HIST",
        "room_num": "67319",
        "desc": "US Hst:First Encounters to Pre"
    },
    {
        "major": "HIST",
        "room_num": "67320",
        "desc": "United States Economic History"
    },
    {
        "major": "HIST",
        "room_num": "67321",
        "desc": "United States\u2019 Origins"
    },
    {
        "major": "HIST",
        "room_num": "67322",
        "desc": "Urban America Blacks"
    },
    {
        "major": "HIST",
        "room_num": "67323",
        "desc": "Us Themes 1607-1788"
    },
    {
        "major": "HIST",
        "room_num": "67324",
        "desc": "Ushst Them 1877-1914"
    },
    {
        "major": "HIST",
        "room_num": "67325",
        "desc": "Vietnam At War&Peace"
    },
    {
        "major": "HIST",
        "room_num": "67326",
        "desc": "Vietnam and America: 1945-1975"
    },
    {
        "major": "HIST",
        "room_num": "67327",
        "desc": "War & Soc/Mod Amer"
    },
    {
        "major": "HIST",
        "room_num": "67328",
        "desc": "War and Society"
    },
    {
        "major": "HIST",
        "room_num": "67329",
        "desc": "West & World: Africa/Eur"
    },
    {
        "major": "HIST",
        "room_num": "67330",
        "desc": "West & Wrld:Crs Cult Encounter"
    },
    {
        "major": "HIST",
        "room_num": "67331",
        "desc": "West Civ To 1500"
    },
    {
        "major": "HIST",
        "room_num": "67332",
        "desc": "West Civilization since 1500"
    },
    {
        "major": "HIST",
        "room_num": "67333",
        "desc": "West Eurp 400-1000ce"
    },
    {
        "major": "HIST",
        "room_num": "67334",
        "desc": "White Men/Indians"
    },
    {
        "major": "HIST",
        "room_num": "67335",
        "desc": "Women Hst/Fem Theory"
    },
    {
        "major": "HIST",
        "room_num": "67336",
        "desc": "Women in Latin America"
    },
    {
        "major": "HIST",
        "room_num": "67337",
        "desc": "World Civilization I"
    },
    {
        "major": "HIST",
        "room_num": "67338",
        "desc": "World Civilization II"
    },
    {
        "major": "HIST",
        "room_num": "67339",
        "desc": "World War II"
    },
    {
        "major": "HIST",
        "room_num": "67340",
        "desc": "Your Parents\u2019 America"
    }
]