[
    {
        "school": "KCC01",
        "major": "PERM",
        "room_num": "63857",
        "room_desc": "Permit 1 Credit"
    },
    {
        "school": "KCC01",
        "major": "PERM",
        "room_num": "63858",
        "room_desc": "Permit 2 Credits"
    },
    {
        "school": "KCC01",
        "major": "PERM",
        "room_num": "63859",
        "room_desc": "Permit 2.5 Credits"
    },
    {
        "school": "KCC01",
        "major": "PERM",
        "room_num": "63860",
        "room_desc": "Permit 3 Credits"
    },
    {
        "school": "KCC01",
        "major": "PERM",
        "room_num": "63861",
        "room_desc": "Permit 4 Credits"
    },
    {
        "school": "KCC01",
        "major": "PERM",
        "room_num": "63862",
        "room_desc": "Permit 5 Credits"
    },
    {
        "school": "KCC01",
        "major": "PERM",
        "room_num": "63863",
        "room_desc": "Permit 6 Credits"
    },
    {
        "school": "KCC01",
        "major": "PERM",
        "room_num": "63864",
        "room_desc": "Permit Course"
    },
    {
        "school": "KCC01",
        "major": "PERM",
        "room_num": "88481",
        "room_desc": "PERM"
    }
]