[
    {
        "school": "JJC01",
        "major": "BIOL",
        "room_num": "19656",
        "room_desc": "Anatomy & Physio Lab"
    },
    {
        "school": "JJC01",
        "major": "BIOL",
        "room_num": "19657",
        "room_desc": "Bio/Gender Sexuality"
    },
    {
        "school": "JJC01",
        "major": "BIOL",
        "room_num": "19658",
        "room_desc": "Biology Tr Cred"
    },
    {
        "school": "JJC01",
        "major": "BIOL",
        "room_num": "19659",
        "room_desc": "Cell & Molecular Bio Capstone"
    },
    {
        "school": "JJC01",
        "major": "BIOL",
        "room_num": "19660",
        "room_desc": "Cell Biology"
    },
    {
        "school": "JJC01",
        "major": "BIOL",
        "room_num": "19661",
        "room_desc": "Fac Mentored Research Experien"
    },
    {
        "school": "JJC01",
        "major": "BIOL",
        "room_num": "19662",
        "room_desc": "Forensic Biology"
    },
    {
        "school": "JJC01",
        "major": "BIOL",
        "room_num": "19663",
        "room_desc": "Forensic DNA Analysis & Interp"
    },
    {
        "school": "JJC01",
        "major": "BIOL",
        "room_num": "19664",
        "room_desc": "Forensic Pathology"
    },
    {
        "school": "JJC01",
        "major": "BIOL",
        "room_num": "19665",
        "room_desc": "Genetics"
    },
    {
        "school": "JJC01",
        "major": "BIOL",
        "room_num": "19666",
        "room_desc": "Human Anat/Phys Lab"
    },
    {
        "school": "JJC01",
        "major": "BIOL",
        "room_num": "19667",
        "room_desc": "Human Pathology"
    },
    {
        "school": "JJC01",
        "major": "BIOL",
        "room_num": "19668",
        "room_desc": "Human Physiology"
    },
    {
        "school": "JJC01",
        "major": "BIOL",
        "room_num": "19669",
        "room_desc": "Independent Study 200-level"
    },
    {
        "school": "JJC01",
        "major": "BIOL",
        "room_num": "19670",
        "room_desc": "Independent Study 300-level"
    },
    {
        "school": "JJC01",
        "major": "BIOL",
        "room_num": "19671",
        "room_desc": "Independent Study 400-level"
    },
    {
        "school": "JJC01",
        "major": "BIOL",
        "room_num": "19672",
        "room_desc": "Microbiology"
    },
    {
        "school": "JJC01",
        "major": "BIOL",
        "room_num": "19673",
        "room_desc": "Microbiology Laboratory"
    },
    {
        "school": "JJC01",
        "major": "BIOL",
        "room_num": "19674",
        "room_desc": "Modern Biology I"
    },
    {
        "school": "JJC01",
        "major": "BIOL",
        "room_num": "19675",
        "room_desc": "Modern Biology I-B"
    },
    {
        "school": "JJC01",
        "major": "BIOL",
        "room_num": "19676",
        "room_desc": "Modern Biology II"
    },
    {
        "school": "JJC01",
        "major": "BIOL",
        "room_num": "19677",
        "room_desc": "Molecular Biology"
    },
    {
        "school": "JJC01",
        "major": "BIOL",
        "room_num": "19678",
        "room_desc": "Paced Modern Biology I-A"
    },
    {
        "school": "JJC01",
        "major": "BIOL",
        "room_num": "19679",
        "room_desc": "Selected Topics in Biology"
    },
    {
        "school": "JJC01",
        "major": "BIOL",
        "room_num": "19680",
        "room_desc": "Selected Topics: Biology w/Lab"
    }
]