[
    {
        "school": "JJC01",
        "major": "GOVT",
        "room_num": "20598",
        "room_desc": "Adm Personnel Res"
    },
    {
        "school": "JJC01",
        "major": "GOVT",
        "room_num": "20599",
        "room_desc": "American Pol.Thought"
    },
    {
        "school": "JJC01",
        "major": "GOVT",
        "room_num": "20600",
        "room_desc": "American Political Philosophy"
    },
    {
        "school": "JJC01",
        "major": "GOVT",
        "room_num": "20601",
        "room_desc": "Budgeting"
    },
    {
        "school": "JJC01",
        "major": "GOVT",
        "room_num": "20602",
        "room_desc": "Comp Urban Pol Sys"
    },
    {
        "school": "JJC01",
        "major": "GOVT",
        "room_num": "20603",
        "room_desc": "Const & Crimnl Jstc"
    },
    {
        "school": "JJC01",
        "major": "GOVT",
        "room_num": "20604",
        "room_desc": "Crim Law Pol Admin"
    },
    {
        "school": "JJC01",
        "major": "GOVT",
        "room_num": "20605",
        "room_desc": "Cuny Wash Dc Intrnsh"
    },
    {
        "school": "JJC01",
        "major": "GOVT",
        "room_num": "20606",
        "room_desc": "Government Elective Credit"
    },
    {
        "school": "JJC01",
        "major": "GOVT",
        "room_num": "20607",
        "room_desc": "Honors Tutorial"
    },
    {
        "school": "JJC01",
        "major": "GOVT",
        "room_num": "20608",
        "room_desc": "Independent Study"
    },
    {
        "school": "JJC01",
        "major": "GOVT",
        "room_num": "20609",
        "room_desc": "Interdisc Gov"
    },
    {
        "school": "JJC01",
        "major": "GOVT",
        "room_num": "20610",
        "room_desc": "Law/Pol Sex Orient"
    },
    {
        "school": "JJC01",
        "major": "GOVT",
        "room_num": "20611",
        "room_desc": "News Media & Just"
    },
    {
        "school": "JJC01",
        "major": "GOVT",
        "room_num": "20612",
        "room_desc": "Nyc Politics &Policy"
    },
    {
        "school": "JJC01",
        "major": "GOVT",
        "room_num": "20613",
        "room_desc": "Nys Assembly/Senate"
    },
    {
        "school": "JJC01",
        "major": "GOVT",
        "room_num": "20614",
        "room_desc": "Planning"
    },
    {
        "school": "JJC01",
        "major": "GOVT",
        "room_num": "20615",
        "room_desc": "Pol Prty Prss Gps"
    },
    {
        "school": "JJC01",
        "major": "GOVT",
        "room_num": "20616",
        "room_desc": "Pol Theory Crj"
    },
    {
        "school": "JJC01",
        "major": "GOVT",
        "room_num": "20617",
        "room_desc": "Pol Transnatnl Crime"
    },
    {
        "school": "JJC01",
        "major": "GOVT",
        "room_num": "20618",
        "room_desc": "Polit Judicial Proc"
    },
    {
        "school": "JJC01",
        "major": "GOVT",
        "room_num": "20619",
        "room_desc": "Politic Glob Inequal"
    },
    {
        "school": "JJC01",
        "major": "GOVT",
        "room_num": "20620",
        "room_desc": "Political Sociology"
    },
    {
        "school": "JJC01",
        "major": "GOVT",
        "room_num": "20621",
        "room_desc": "Productivity Mgmt"
    },
    {
        "school": "JJC01",
        "major": "GOVT",
        "room_num": "20622",
        "room_desc": "Reparation Afram Exp"
    },
    {
        "school": "JJC01",
        "major": "GOVT",
        "room_num": "20623",
        "room_desc": "Sem Civil Rgts Lib"
    },
    {
        "school": "JJC01",
        "major": "GOVT",
        "room_num": "20624",
        "room_desc": "Sem Nyc Politics"
    },
    {
        "school": "JJC01",
        "major": "GOVT",
        "room_num": "20625",
        "room_desc": "Seminar in Government"
    },
    {
        "school": "JJC01",
        "major": "GOVT",
        "room_num": "20626",
        "room_desc": "Semr&Intrn Nyc Go"
    },
    {
        "school": "JJC01",
        "major": "GOVT",
        "room_num": "20627",
        "room_desc": "St:Women & Politics"
    },
    {
        "school": "JJC01",
        "major": "GOVT",
        "room_num": "20628",
        "room_desc": "State Crts & Cons Law"
    },
    {
        "school": "JJC01",
        "major": "GOVT",
        "room_num": "20629",
        "room_desc": "The Chief Executive"
    },
    {
        "school": "JJC01",
        "major": "GOVT",
        "room_num": "20630",
        "room_desc": "Transnational Crime"
    },
    {
        "school": "JJC01",
        "major": "GOVT",
        "room_num": "20631",
        "room_desc": "United Nations Systm"
    },
    {
        "school": "JJC01",
        "major": "GOVT",
        "room_num": "20632",
        "room_desc": "Urban Politics"
    },
    {
        "school": "JJC01",
        "major": "GOVT",
        "room_num": "20633",
        "room_desc": "Us For Plcy Latin Am"
    },
    {
        "school": "JJC01",
        "major": "GOVT",
        "room_num": "20634",
        "room_desc": "Women And Law"
    },
    {
        "school": "JJC01",
        "major": "GOVT",
        "room_num": "87068",
        "room_desc": "GOVT"
    }
]