[
    {
        "school": "GRD01",
        "major": "PERM",
        "room_num": "8221",
        "room_desc": "American Museum of Natrl Hist"
    },
    {
        "school": "GRD01",
        "major": "PERM",
        "room_num": "8222",
        "room_desc": "BMCC"
    },
    {
        "school": "GRD01",
        "major": "PERM",
        "room_num": "8223",
        "room_desc": "Baruch College"
    },
    {
        "school": "GRD01",
        "major": "PERM",
        "room_num": "8224",
        "room_desc": "Bronx Community College"
    },
    {
        "school": "GRD01",
        "major": "PERM",
        "room_num": "8225",
        "room_desc": "Brooklyn College"
    },
    {
        "school": "GRD01",
        "major": "PERM",
        "room_num": "8226",
        "room_desc": "CUNY Law School"
    },
    {
        "school": "GRD01",
        "major": "PERM",
        "room_num": "8227",
        "room_desc": "City College"
    },
    {
        "school": "GRD01",
        "major": "PERM",
        "room_num": "8228",
        "room_desc": "College of Staten Island"
    },
    {
        "school": "GRD01",
        "major": "PERM",
        "room_num": "8229",
        "room_desc": "Hunter College"
    },
    {
        "school": "GRD01",
        "major": "PERM",
        "room_num": "8230",
        "room_desc": "John Jay College"
    },
    {
        "school": "GRD01",
        "major": "PERM",
        "room_num": "8231",
        "room_desc": "Kingsborough Community College"
    },
    {
        "school": "GRD01",
        "major": "PERM",
        "room_num": "8232",
        "room_desc": "Lehman College"
    },
    {
        "school": "GRD01",
        "major": "PERM",
        "room_num": "8233",
        "room_desc": "NYC College of Technology"
    },
    {
        "school": "GRD01",
        "major": "PERM",
        "room_num": "8234",
        "room_desc": "Permit Out"
    },
    {
        "school": "GRD01",
        "major": "PERM",
        "room_num": "8235",
        "room_desc": "Queens College"
    },
    {
        "school": "GRD01",
        "major": "PERM",
        "room_num": "8236",
        "room_desc": "Queensborough CC"
    },
    {
        "school": "GRD01",
        "major": "PERM",
        "room_num": "8237",
        "room_desc": "School of Journalism"
    },
    {
        "school": "GRD01",
        "major": "PERM",
        "room_num": "8238",
        "room_desc": "School of Labor&Urban Studies"
    },
    {
        "school": "GRD01",
        "major": "PERM",
        "room_num": "8239",
        "room_desc": "School of Professional Studies"
    },
    {
        "school": "GRD01",
        "major": "PERM",
        "room_num": "8240",
        "room_desc": "School of Public Health"
    },
    {
        "school": "GRD01",
        "major": "PERM",
        "room_num": "8241",
        "room_desc": "York College"
    }
]